drf_insights_pagination/__init__.py
drf_insights_pagination/pagination.py
drf_insights_pagination/settings.py
drf_insights_pagination-1.0.1.dist-info/LICENSE
drf_insights_pagination-1.0.1.dist-info/WHEEL
drf_insights_pagination-1.0.1.dist-info/METADATA
drf_insights_pagination-1.0.1.dist-info/RECORD
