Metadata-Version: 2.1
Name: drf-insights-pagination
Version: 1.0.1
Summary: Provides pagination class that adheres to Insights IPP-12.
Home-page: https://gitlab.com/cloudigrade/libraries/drf-insights-pagination
License: GPL-3.0-or-later
Keywords: djangorestframework,drf,pagination,insights,ipp-12
Author: Cloudigrade Dev Team
Author-email: doppler-dev@redhat.com
Requires-Python: >=3.6,<4.0
Classifier: Development Status :: 5 - Production/Stable
Classifier: Intended Audience :: Developers
Classifier: License :: OSI Approved :: GNU General Public License v3 (GPLv3)
Classifier: License :: OSI Approved :: GNU General Public License v3 or later (GPLv3+)
Classifier: Operating System :: OS Independent
Classifier: Programming Language :: Python
Classifier: Programming Language :: Python :: 3
Classifier: Programming Language :: Python :: 3.6
Classifier: Programming Language :: Python :: 3.7
Classifier: Programming Language :: Python :: 3.8
Classifier: Programming Language :: Python :: 3.9
Classifier: Topic :: Software Development
Classifier: Topic :: Software Development :: Libraries
Classifier: Topic :: Software Development :: Libraries :: Python Modules
Requires-Dist: djangorestframework
Project-URL: Repository, https://gitlab.com/cloudigrade/libraries/drf-insights-pagination
